ecprint/__init__.py
ecprint/cprint.py
ecprint-0.1.3.dist-info/LICENSE
ecprint-0.1.3.dist-info/METADATA
ecprint-0.1.3.dist-info/WHEEL
ecprint-0.1.3.dist-info/top_level.txt
ecprint-0.1.3.dist-info/RECORD
